LICENSE
MANIFEST.in
README.md
setup.cfg
setup.py
docker_registry/__init__.py
docker_registry/app.py
docker_registry/images.py
docker_registry/index.py
docker_registry/run.py
docker_registry/search.py
docker_registry/status.py
docker_registry/tags.py
docker_registry/toolkit.py
docker_registry/wsgi.py
docker_registry.egg-info/PKG-INFO
docker_registry.egg-info/SOURCES.txt
docker_registry.egg-info/dependency_links.txt
docker_registry.egg-info/entry_points.txt
docker_registry.egg-info/namespace_packages.txt
docker_registry.egg-info/not-zip-safe
docker_registry.egg-info/requires.txt
docker_registry.egg-info/top_level.txt
docker_registry/../config/boto.cfg
docker_registry/../config/config_mirror.yml
docker_registry/../config/config_sample.yml
docker_registry/../config/gunicorn_config.py
docker_registry/drivers/__init__.py
docker_registry/drivers/s3.py
docker_registry/lib/__init__.py
docker_registry/lib/cache.py
docker_registry/lib/checksums.py
docker_registry/lib/config.py
docker_registry/lib/layers.py
docker_registry/lib/mirroring.py
docker_registry/lib/rlock.py
docker_registry/lib/rqueue.py
docker_registry/lib/signals.py
docker_registry/lib/xtarfile.py
docker_registry/lib/index/__init__.py
docker_registry/lib/index/db.py
docker_registry/server/__init__.py
docker_registry/server/env.py
docker_registry/storage/__init__.py
requirements/main.txt
requirements/style.txt
requirements/test.txt