Metadata-Version: 1.1
Name: docker-registry
Version: 0.8.1
Summary: Registry server for Docker
Home-page: https://github.com/dotcloud/docker-registry
Author: Docker Registry Contributors
Author-email: docker-dev@googlegroups.com
License: 
